RK4_Propagator/RK4_Propagator.py
RK4_Propagator/__init__.py
src/__init__.py
RK4_Propagator-0.2.dist-info/METADATA
RK4_Propagator-0.2.dist-info/WHEEL
RK4_Propagator-0.2.dist-info/top_level.txt
RK4_Propagator-0.2.dist-info/RECORD
