Metadata-Version: 2.1
Name: RK4-Propagator
Version: 0.2
Summary: A package that can approximate orbital motion around the Earth with 4th order accuracy. To import, use the command "from RK4_Propagator import RK4_Propagator"
Home-page: https://github.com/zackgwillson/RK4_Propagator
Author: Zack Willson
Author-email: 
Requires-Dist: numpy
